no_puzzle_captcha/__init__.py
no_puzzle_captcha/_solver.py
no_puzzle_captcha/_transforms.py
no_puzzle_captcha-1.1.1.dist-info/LICENSE
no_puzzle_captcha-1.1.1.dist-info/METADATA
no_puzzle_captcha-1.1.1.dist-info/WHEEL
no_puzzle_captcha-1.1.1.dist-info/RECORD
