Metadata-Version: 2.3
Name: No-Puzzle-Captcha
Version: 1.1.1
Summary: Lightweight Library for Slide Puzzle Captcha Solving
License: MIT
Author: Harry Huang
Author-email: harryhuang2652@qq.com
Requires-Python: >=3.8,<4
Classifier: Programming Language :: Python :: 3
Classifier: License :: OSI Approved :: MIT License
Classifier: Operating System :: OS Independent
Requires-Dist: opencv-python (>=4.1,<5)
